django_nimble-0.0.1.post2.dist-info/DESCRIPTION.rst
django_nimble-0.0.1.post2.dist-info/METADATA
django_nimble-0.0.1.post2.dist-info/RECORD
django_nimble-0.0.1.post2.dist-info/WHEEL
django_nimble-0.0.1.post2.dist-info/metadata.json
django_nimble-0.0.1.post2.dist-info/top_level.txt
nimble/__init__.py
nimble/admin.py
nimble/apps.py
nimble/urls.py
nimble/__pycache__/__init__.cpython-35.pyc
nimble/__pycache__/admin.cpython-35.pyc
nimble/__pycache__/apps.cpython-35.pyc
nimble/__pycache__/urls.cpython-35.pyc
nimble/forms/__init__.py
nimble/forms/profile.py
nimble/forms/user.py
nimble/forms/__pycache__/__init__.cpython-35.pyc
nimble/forms/__pycache__/profile.cpython-35.pyc
nimble/forms/__pycache__/user.cpython-35.pyc
nimble/migrations/0001_initial.py
nimble/migrations/0002_profile_theme.py
nimble/migrations/__init__.py
nimble/migrations/__pycache__/0001_initial.cpython-35.pyc
nimble/migrations/__pycache__/0002_profile_theme.cpython-35.pyc
nimble/migrations/__pycache__/0003_auto_20161103_2137.cpython-35.pyc
nimble/migrations/__pycache__/__init__.cpython-35.pyc
nimble/models/__init__.py
nimble/models/profile.py
nimble/models/__pycache__/__init__.cpython-35.pyc
nimble/models/__pycache__/profile.cpython-35.pyc
nimble/serializers/__init__.py
nimble/serializers/profile.py
nimble/serializers/user.py
nimble/serializers/__pycache__/__init__.cpython-35.pyc
nimble/serializers/__pycache__/profile.cpython-35.pyc
nimble/serializers/__pycache__/user.cpython-35.pyc
nimble/templates/nimble/base.html
nimble/templates/nimble/control_panel.html
nimble/templates/nimble/dashboard.html
nimble/templates/nimble/includes/navbar.html
nimble/templates/nimble/includes/style.html
nimble/templates/rest_framework/api.html
nimble/views/__init__.py
nimble/views/control_panel.py
nimble/views/dashboard.py
nimble/views/index.py
nimble/views/__pycache__/__init__.cpython-35.pyc
nimble/views/__pycache__/control_panel.cpython-35.pyc
nimble/views/__pycache__/dashboard.cpython-35.pyc
nimble/views/__pycache__/index.cpython-35.pyc
nimble/views/__pycache__/multiform.cpython-35.pyc
