Metadata-Version: 2.0
Name: django-nimble
Version: 0.0.1.post2
Summary: Nimble Project Management
Home-page: https://pypi.python.org/pypi/django-nimble
Author: Karl Odie
Author-email: karlodie@gmail.com
License: BSD
Platform: UNKNOWN
Classifier: Environment :: Web Environment
Classifier: Framework :: Django
Classifier: Operating System :: OS Independent
Classifier: Programming Language :: Python
Classifier: Programming Language :: Python :: 3
Classifier: Topic :: Internet :: WWW/HTTP
Requires-Dist: Markdown
Requires-Dist: django
Requires-Dist: django-bootstrap3
Requires-Dist: djangorestframework
